fenv/__init__.py
fenv/__main__.py
fenv/env_all.py
fenv/fenv.py
fenv/manage_file.py
fenv/state_env.py
fenv/assets/__init__.py
fenv/assets/commands.py
fenv/customizes/__init__.py
fenv/customizes/colors.py
Fenv-0.0.12.4.dist-info/METADATA
Fenv-0.0.12.4.dist-info/WHEEL
Fenv-0.0.12.4.dist-info/entry_points.txt
Fenv-0.0.12.4.dist-info/top_level.txt
Fenv-0.0.12.4.dist-info/RECORD
