Metadata-Version: 2.1
Name: Fenv
Version: 0.0.12.4
Summary: Generate a folder, establish a virtual environment with a single command.
Author: wk18k (watchakorn-18k)
Author-email: <porton555@gmail.com>
Keywords: python,virtualenv,create file,create folder,fenv,wk-18k
Classifier: Development Status :: 1 - Planning
Classifier: Intended Audience :: Developers
Classifier: License :: OSI Approved :: MIT License
Classifier: Natural Language :: English
Classifier: Programming Language :: Python :: 3.10
Classifier: Programming Language :: Python :: 3.11
Classifier: Operating System :: Unix
Classifier: Operating System :: Microsoft :: Windows
Requires-Dist: virtualenv
